setup.cfg
setup.py
lib/playeah/__init__.py
lib/playeah/hello.py
lib/playeah.egg-info/PKG-INFO
lib/playeah.egg-info/SOURCES.txt
lib/playeah.egg-info/dependency_links.txt
lib/playeah.egg-info/top_level.txt