Metadata-Version: 1.1
Name: playeah
Version: 0.1
Summary: playeah
Home-page: https://github.com/fmcevoy/playeah
Author: Fintan McEvoy
Author-email: fintan.mcevoy@gmail.com
License: UNKNOWN
Download-URL: https://github.com/fmcevoy/playeah/tarball/0.1
Platform: UNKNOWN
